pyDAPAccess
