Metadata-Version: 1.1
Name: pyDAPAccess
Version: 0.1.3
Summary: CMSIS-DAP debugger access for Python
Home-page: https://github.com/mbedmicro/pyDAPAccess
Author: Martin Kojtal, Russ Butler
Author-email: martin.kojtal@arm.com, russ.butler@arm.com
License: Apache 2.0
Platform: UNKNOWN
Classifier: Development Status :: 4 - Beta
Classifier: License :: OSI Approved :: Apache Software License
Classifier: Programming Language :: Python
